{"user_num": 11687, "total_rank": [{"username": "gansha9451", "global_ranking": 0, "user_slug": "gansha9451", "finish_time": 1587869036, "rank": 5426, "contest_id": 340, "score": 3, "data_region": "US", "country_code": "IN", "country_name": "India"}, {"username": "rishav19", "global_ranking": 0, "user_slug": "rishav19", "finish_time": 1587869037, "rank": 5427, "contest_id": 340, "score": 3, "data_region": "US", "country_code": "", "country_name": null}, {"username": "cyqq74", "global_ranking": 0, "user_slug": "cyqq74", "finish_time": 1587869038, "rank": 5428, "contest_id": 340, "score": 3, "data_region": "US", "country_code": "", "country_name": null}, {"username": "agw02010", "global_ranking": 0, "user_slug": "agw02010", "finish_time": 1587869038, "rank": 5429, "contest_id": 340, "score": 3, "data_region": "US", "country_code": "", "country_name": null}, {"username": "mahesh767", "global_ranking": 0, "user_slug": "mahesh767", "finish_time": 1587869038, "rank": 5430, "contest_id": 340, "score": 3, "data_region": "US", "country_code": "", "country_name": null}, {"username": "anil111", "global_ranking": 0, "user_slug": "anil111", "finish_time": 1587869039, "rank": 5431, "contest_id": 340, "score": 3, "data_region": "US", "country_code": "IN", "country_name": "India"}, {"username": "bei-ming-wu-yu", "global_ranking": 0, "user_slug": "bei-ming-wu-yu", "finish_time": 1587869040, "rank": 5432, "contest_id": 185, "score": 3, "data_region": "CN", "country_code": "", "country_name": ""}, {"username": "SusmithaM", "global_ranking": 0, "user_slug": "susmitham", "finish_time": 1587869041, "rank": 5433, "contest_id": 340, "score": 3, "data_region": "US", "country_code": "US", "country_name": "United States"}, {"username": "zengjiahuizjh", "global_ranking": 0, "user_slug": "zengjiahuizjh", "finish_time": 1587869041, "rank": 5434, "contest_id": 340, "score": 3, "data_region": "US", "country_code": "", "country_name": null}, {"username": "Arrekhey", "global_ranking": 0, "user_slug": "arrekhey", "finish_time": 1587869043, "rank": 5435, "contest_id": 340, "score": 3, "data_region": "US", "country_code": "IN", "country_name": "India"}, {"username": "user7862p", "global_ranking": 0, "user_slug": "user7862p", "finish_time": 1587869043, "rank": 5436, "contest_id": 340, "score": 3, "data_region": "US", "country_code": "US", "country_name": "United States"}, {"username": "491", "global_ranking": 0, "user_slug": "491", "finish_time": 1587869044, "rank": 5437, "contest_id": 185, "score": 3, "data_region": "CN", "country_code": "", "country_name": ""}, {"username": "shradha_k", "global_ranking": 0, "user_slug": "shradha_k", "finish_time": 1587869044, "rank": 5438, "contest_id": 340, "score": 3, "data_region": "US", "country_code": "", "country_name": null}, {"username": "lsc268", "global_ranking": 0, "user_slug": "lsc268", "finish_time": 1587869045, "rank": 5439, "contest_id": 340, "score": 3, "data_region": "US", "country_code": "", "country_name": null}, {"username": "Sabbi_coder", "global_ranking": 0, "user_slug": "sabbi_coder", "finish_time": 1587869046, "rank": 5440, "contest_id": 340, "score": 3, "data_region": "US", "country_code": "IN", "country_name": "India"}, {"username": "biljun-zheng-jiu-bu-kai-xin", "global_ranking": 0, "user_slug": "biljun-zheng-jiu-bu-kai-xin", "finish_time": 1587869046, "rank": 5441, "contest_id": 185, "score": 3, "data_region": "CN", "country_code": "", "country_name": "\u4e2d\u56fd"}, {"username": "chen_de_se", "global_ranking": 0, "user_slug": "chen_de_se", "finish_time": 1587869047, "rank": 5442, "contest_id": 185, "score": 3, "data_region": "CN", "country_code": "", "country_name": "\u4e2d\u56fd"}, {"username": "Prodyte", "global_ranking": 0, "user_slug": "prodyte", "finish_time": 1587869047, "rank": 5443, "contest_id": 340, "score": 3, "data_region": "US", "country_code": "IN", "country_name": "India"}, {"username": "node", "global_ranking": 0, "user_slug": "node", "finish_time": 1587869048, "rank": 5444, "contest_id": 340, "score": 3, "data_region": "US", "country_code": "", "country_name": null}, {"username": "HRITIK_AKOLKAR", "global_ranking": 0, "user_slug": "hritik_akolkar", "finish_time": 1587869050, "rank": 5445, "contest_id": 340, "score": 3, "data_region": "US", "country_code": "IN", "country_name": "India"}, {"username": "comity", "global_ranking": 0, "user_slug": "comity", "finish_time": 1587869050, "rank": 5446, "contest_id": 340, "score": 3, "data_region": "US", "country_code": "", "country_name": ""}, {"username": "oneplusfive", "global_ranking": 0, "user_slug": "oneplusfive", "finish_time": 1587869050, "rank": 5447, "contest_id": 340, "score": 3, "data_region": "US", "country_code": "", "country_name": null}, {"username": "marccarre", "global_ranking": 0, "user_slug": "marccarre", "finish_time": 1587869051, "rank": 5448, "contest_id": 340, "score": 3, "data_region": "US", "country_code": "JP", "country_name": "Japan"}, {"username": "poojaagrwl13", "global_ranking": 0, "user_slug": "poojaagrwl13", "finish_time": 1587869051, "rank": 5449, "contest_id": 340, "score": 3, "data_region": "US", "country_code": "", "country_name": null}, {"username": "sathyanarayananc120", "global_ranking": 0, "user_slug": "sathyanarayananc120", "finish_time": 1587869051, "rank": 5450, "contest_id": 340, "score": 3, "data_region": "US", "country_code": "", "country_name": null}], "questions": [{"credit": 3, "title": "Maximum Score After Splitting a String", "id": 1358, "title_slug": "maximum-score-after-splitting-a-string", "question_id": 1537}, {"credit": 4, "title": "Maximum Points You Can Obtain from Cards", "id": 1359, "title_slug": "maximum-points-you-can-obtain-from-cards", "question_id": 1538}, {"credit": 5, "title": "Diagonal Traverse II", "id": 1360, "title_slug": "diagonal-traverse-ii", "question_id": 1539}, {"credit": 6, "title": "Constrained Subsequence Sum", "id": 1361, "title_slug": "constrained-subsequence-sum", "question_id": 1286}], "time": 1592772669.0488913, "is_past": true, "submissions": [{"1537": {"status": 10, "submission_id": 330159204, "fail_count": 1, "contest_id": 340, "data_region": "US", "date": 1587868736, "id": 2283683, "question_id": 1537}}, {"1537": {"status": 10, "submission_id": 330163907, "fail_count": 0, "contest_id": 340, "data_region": "US", "date": 1587869037, "id": 2286853, "question_id": 1537}}, {"1537": {"status": 10, "submission_id": 330163911, "fail_count": 0, "contest_id": 340, "data_region": "US", "date": 1587869038, "id": 2286856, "question_id": 1537}}, {"1537": {"status": 10, "submission_id": 330159243, "fail_count": 1, "contest_id": 340, "data_region": "US", "date": 1587868738, "id": 2283707, "question_id": 1537}}, {"1537": {"status": 10, "submission_id": 330163929, "fail_count": 0, "contest_id": 340, "data_region": "US", "date": 1587869038, "id": 2286869, "question_id": 1537}}, {"1537": {"status": 10, "submission_id": 330163945, "fail_count": 0, "contest_id": 340, "data_region": "US", "date": 1587869039, "id": 2286879, "question_id": 1537}}, {"1537": {"status": 10, "submission_id": 66004492, "fail_count": 0, "contest_id": 185, "data_region": "CN", "date": 1587869040, "id": 494530, "question_id": 1537}}, {"1537": {"status": 10, "submission_id": 330163969, "fail_count": 0, "contest_id": 340, "data_region": "US", "date": 1587869041, "id": 2286896, "question_id": 1537}}, {"1537": {"status": 10, "submission_id": 330163974, "fail_count": 0, "contest_id": 340, "data_region": "US", "date": 1587869041, "id": 2286901, "question_id": 1537}}, {"1537": {"status": 10, "submission_id": 330163992, "fail_count": 0, "contest_id": 340, "data_region": "US", "date": 1587869043, "id": 2286908, "question_id": 1537}}, {"1537": {"status": 10, "submission_id": 330164000, "fail_count": 0, "contest_id": 340, "data_region": "US", "date": 1587869043, "id": 2286915, "question_id": 1537}}, {"1537": {"status": 10, "submission_id": 66004519, "fail_count": 0, "contest_id": 185, "data_region": "CN", "date": 1587869044, "id": 494542, "question_id": 1537}}, {"1537": {"status": 10, "submission_id": 330164015, "fail_count": 0, "contest_id": 340, "data_region": "US", "date": 1587869044, "id": 2286925, "question_id": 1537}}, {"1537": {"status": 10, "submission_id": 330159381, "fail_count": 1, "contest_id": 340, "data_region": "US", "date": 1587868745, "id": 2283802, "question_id": 1537}}, {"1537": {"status": 10, "submission_id": 330159399, "fail_count": 1, "contest_id": 340, "data_region": "US", "date": 1587868746, "id": 2283812, "question_id": 1537}}, {"1537": {"status": 10, "submission_id": 66001262, "fail_count": 1, "contest_id": 185, "data_region": "CN", "date": 1587868746, "id": 493441, "question_id": 1537}}, {"1537": {"status": 10, "submission_id": 66004547, "fail_count": 0, "contest_id": 185, "data_region": "CN", "date": 1587869047, "id": 494554, "question_id": 1537}}, {"1537": {"status": 10, "submission_id": 330164051, "fail_count": 0, "contest_id": 340, "data_region": "US", "date": 1587869047, "id": 2286951, "question_id": 1537}}, {"1537": {"status": 10, "submission_id": 330159430, "fail_count": 1, "contest_id": 340, "data_region": "US", "date": 1587868748, "id": 2283835, "question_id": 1537}}, {"1537": {"status": 10, "submission_id": 330159452, "fail_count": 1, "contest_id": 340, "data_region": "US", "date": 1587868750, "id": 2283849, "question_id": 1537}}, {"1537": {"status": 10, "submission_id": 330164077, "fail_count": 0, "contest_id": 340, "data_region": "US", "date": 1587869050, "id": 2286967, "question_id": 1537}}, {"1537": {"status": 10, "submission_id": 330164087, "fail_count": 0, "contest_id": 340, "data_region": "US", "date": 1587869050, "id": 2286972, "question_id": 1537}}, {"1537": {"status": 10, "submission_id": 330154661, "fail_count": 2, "contest_id": 340, "data_region": "US", "date": 1587868451, "id": 2280566, "question_id": 1537}}, {"1537": {"status": 10, "submission_id": 330164102, "fail_count": 0, "contest_id": 340, "data_region": "US", "date": 1587869051, "id": 2286982, "question_id": 1537}}, {"1537": {"status": 10, "submission_id": 330159465, "fail_count": 1, "contest_id": 340, "data_region": "US", "date": 1587868751, "id": 2283859, "question_id": 1537}}]}