{"user_num": 15383, "total_rank": [{"username": "rkr_725", "global_ranking": 0, "user_slug": "rkr_725", "finish_time": 1596335400, "rank": 11651, "contest_id": 382, "score": 0, "data_region": "US", "country_code": "IN", "country_name": "India"}, {"username": "sree_pavan", "global_ranking": 0, "user_slug": "sree_pavan", "finish_time": 1596335400, "rank": 11652, "contest_id": 382, "score": 0, "data_region": "US", "country_code": "", "country_name": null}, {"username": "singhsimran1802", "global_ranking": 0, "user_slug": "singhsimran1802", "finish_time": 1596335400, "rank": 11653, "contest_id": 382, "score": 0, "data_region": "US", "country_code": "", "country_name": null}, {"username": "Agent_X", "global_ranking": 0, "user_slug": "agent_x", "finish_time": 1596335400, "rank": 11654, "contest_id": 382, "score": 0, "data_region": "US", "country_code": "", "country_name": null}, {"username": "Trevahok", "global_ranking": 0, "user_slug": "trevahok", "finish_time": 1596335400, "rank": 11655, "contest_id": 382, "score": 0, "data_region": "US", "country_code": "", "country_name": null}, {"username": "Mandar800", "global_ranking": 0, "user_slug": "mandar800", "finish_time": 1596335400, "rank": 11656, "contest_id": 382, "score": 0, "data_region": "US", "country_code": "IN", "country_name": "India"}, {"username": "rafayhassan", "global_ranking": 0, "user_slug": "rafayhassan", "finish_time": 1596335400, "rank": 11657, "contest_id": 382, "score": 0, "data_region": "US", "country_code": "", "country_name": null}, {"username": "netambhardwaj", "global_ranking": 0, "user_slug": "netambhardwaj", "finish_time": 1596335400, "rank": 11658, "contest_id": 382, "score": 0, "data_region": "US", "country_code": "", "country_name": null}, {"username": "Myestery", "global_ranking": 0, "user_slug": "myestery", "finish_time": 1596335400, "rank": 11659, "contest_id": 382, "score": 0, "data_region": "US", "country_code": "", "country_name": null}, {"username": "JohnRoyce", "global_ranking": 0, "user_slug": "johnroyce", "finish_time": 1596335400, "rank": 11660, "contest_id": 382, "score": 0, "data_region": "US", "country_code": "", "country_name": null}, {"username": "duynguyen24501", "global_ranking": 0, "user_slug": "duynguyen24501", "finish_time": 1596335400, "rank": 11661, "contest_id": 382, "score": 0, "data_region": "US", "country_code": "", "country_name": null}, {"username": "royalwhale", "global_ranking": 0, "user_slug": "royalwhale", "finish_time": 1596335400, "rank": 11662, "contest_id": 382, "score": 0, "data_region": "US", "country_code": "US", "country_name": "United States"}, {"username": "nilabhro_29", "global_ranking": 0, "user_slug": "nilabhro_29", "finish_time": 1596335400, "rank": 11663, "contest_id": 382, "score": 0, "data_region": "US", "country_code": "IN", "country_name": "India"}, {"username": "vjakash", "global_ranking": 0, "user_slug": "vjakash", "finish_time": 1596335400, "rank": 11664, "contest_id": 382, "score": 0, "data_region": "US", "country_code": "", "country_name": null}, {"username": "Rohit_chiki", "global_ranking": 0, "user_slug": "rohit_chiki", "finish_time": 1596335400, "rank": 11665, "contest_id": 382, "score": 0, "data_region": "US", "country_code": "", "country_name": null}, {"username": "akhatavk", "global_ranking": 0, "user_slug": "akhatavk", "finish_time": 1596335400, "rank": 11666, "contest_id": 382, "score": 0, "data_region": "US", "country_code": "", "country_name": null}, {"username": "shubhamsharma1808", "global_ranking": 0, "user_slug": "shubhamsharma1808", "finish_time": 1596335400, "rank": 11667, "contest_id": 382, "score": 0, "data_region": "US", "country_code": "", "country_name": null}, {"username": "suzi96", "global_ranking": 0, "user_slug": "suzi96", "finish_time": 1596335400, "rank": 11668, "contest_id": 382, "score": 0, "data_region": "US", "country_code": "IN", "country_name": "India"}, {"username": "user0585b", "global_ranking": 0, "user_slug": "user0585b", "finish_time": 1596335400, "rank": 11669, "contest_id": 382, "score": 0, "data_region": "US", "country_code": "", "country_name": null}, {"username": "dishant26", "global_ranking": 0, "user_slug": "dishant26", "finish_time": 1596335400, "rank": 11670, "contest_id": 382, "score": 0, "data_region": "US", "country_code": "", "country_name": null}, {"username": "merakerr123", "global_ranking": 0, "user_slug": "merakerr123", "finish_time": 1596335400, "rank": 11671, "contest_id": 382, "score": 0, "data_region": "US", "country_code": "", "country_name": null}, {"username": "menavvu23", "global_ranking": 0, "user_slug": "menavvu23", "finish_time": 1596335400, "rank": 11672, "contest_id": 382, "score": 0, "data_region": "US", "country_code": "", "country_name": null}, {"username": "Nimiciaap", "global_ranking": 0, "user_slug": "nimiciaap", "finish_time": 1596335400, "rank": 11673, "contest_id": 382, "score": 0, "data_region": "US", "country_code": "IN", "country_name": "India"}, {"username": "saybeltimofey", "global_ranking": 0, "user_slug": "saybeltimofey", "finish_time": 1596335400, "rank": 11674, "contest_id": 382, "score": 0, "data_region": "US", "country_code": "", "country_name": null}, {"username": "Kunal_Sha", "global_ranking": 0, "user_slug": "kunal_sha", "finish_time": 1596335400, "rank": 11675, "contest_id": 382, "score": 0, "data_region": "US", "country_code": "", "country_name": null}], "questions": [{"credit": 3, "title": "Count Good Triplets", "id": 1526, "title_slug": "count-good-triplets", "question_id": 1656}, {"credit": 4, "title": "Find the Winner of an Array Game", "id": 1527, "title_slug": "find-the-winner-of-an-array-game", "question_id": 1657}, {"credit": 5, "title": "Minimum Swaps to Arrange a Binary Grid", "id": 1528, "title_slug": "minimum-swaps-to-arrange-a-binary-grid", "question_id": 1658}, {"credit": 6, "title": "Get the Maximum Score", "id": 1529, "title_slug": "get-the-maximum-score", "question_id": 1659}], "time": 1596603979.6433368, "is_past": true, "submissions": [{}, {}, {}, {}, {}, {}, {}, {}, {}, {}, {}, {}, {}, {}, {}, {}, {}, {}, {}, {}, {}, {}, {}, {}, {}]}