{"time": 1600278046.5499, "is_past": true, "submissions": [{"693": {"id": 390411, "date": 1507427074, "question_id": 693, "submission_id": 122479759, "status": 10, "contest_id": 59, "data_region": "US", "fail_count": 2}, "694": {"id": 394919, "date": 1507429318, "question_id": 694, "submission_id": 122488571, "status": 10, "contest_id": 59, "data_region": "US", "fail_count": 1}, "695": {"id": 389622, "date": 1507426809, "question_id": 695, "submission_id": 122478476, "status": 10, "contest_id": 59, "data_region": "US", "fail_count": 0}}, {"693": {"id": 389874, "date": 1507426887, "question_id": 693, "submission_id": 122478860, "status": 10, "contest_id": 59, "data_region": "US", "fail_count": 1}, "694": {"id": 395367, "date": 1507429619, "question_id": 694, "submission_id": 122489582, "status": 10, "contest_id": 59, "data_region": "US", "fail_count": 0}, "695": {"id": 391742, "date": 1507427594, "question_id": 695, "submission_id": 122482084, "status": 10, "contest_id": 59, "data_region": "US", "fail_count": 1}}, {"693": {"id": 390786, "date": 1507427212, "question_id": 693, "submission_id": 122480383, "status": 10, "contest_id": 59, "data_region": "US", "fail_count": 3}, "694": {"id": 394936, "date": 1507429330, "question_id": 694, "submission_id": 122488615, "status": 10, "contest_id": 59, "data_region": "US", "fail_count": 0}, "695": {"id": 392537, "date": 1507427957, "question_id": 695, "submission_id": 122483584, "status": 10, "contest_id": 59, "data_region": "US", "fail_count": 0}}, {"693": {"id": 389780, "date": 1507426855, "question_id": 693, "submission_id": 122478712, "status": 10, "contest_id": 59, "data_region": "US", "fail_count": 0}, "694": {"id": 395837, "date": 1507429931, "question_id": 694, "submission_id": 122490712, "status": 10, "contest_id": 59, "data_region": "US", "fail_count": 0}, "695": {"id": 394483, "date": 1507429041, "question_id": 695, "submission_id": 122487612, "status": 10, "contest_id": 59, "data_region": "US", "fail_count": 1}}, {"693": {"id": 393996, "date": 1507428734, "question_id": 693, "submission_id": 122486540, "status": 10, "contest_id": 59, "data_region": "US", "fail_count": 5}, "694": {"id": 393150, "date": 1507428267, "question_id": 694, "submission_id": 122484783, "status": 10, "contest_id": 59, "data_region": "US", "fail_count": 0}, "695": {"id": 390210, "date": 1507427002, "question_id": 695, "submission_id": 122479425, "status": 10, "contest_id": 59, "data_region": "US", "fail_count": 0}}, {"693": {"id": 390472, "date": 1507427098, "question_id": 693, "submission_id": 122479865, "status": 10, "contest_id": 59, "data_region": "US", "fail_count": 0}, "694": {"id": 396316, "date": 1507430244, "question_id": 694, "submission_id": 122491878, "status": 10, "contest_id": 59, "data_region": "US", "fail_count": 0}, "695": {"id": 391945, "date": 1507427677, "question_id": 695, "submission_id": 122482465, "status": 10, "contest_id": 59, "data_region": "US", "fail_count": 0}}, {"693": {"id": 389401, "date": 1507426725, "question_id": 693, "submission_id": 122478135, "status": 10, "contest_id": 59, "data_region": "US", "fail_count": 0}, "694": {"id": 395862, "date": 1507429950, "question_id": 694, "submission_id": 122490788, "status": 10, "contest_id": 59, "data_region": "US", "fail_count": 1}, "695": {"id": 390831, "date": 1507427229, "question_id": 695, "submission_id": 122480461, "status": 10, "contest_id": 59, "data_region": "US", "fail_count": 0}}, {"693": {"id": 390170, "date": 1507426992, "question_id": 693, "submission_id": 122479366, "status": 10, "contest_id": 59, "data_region": "US", "fail_count": 7}, "694": {"id": 392939, "date": 1507428155, "question_id": 694, "submission_id": 122484357, "status": 10, "contest_id": 59, "data_region": "US", "fail_count": 0}, "695": {"id": 391683, "date": 1507427569, "question_id": 695, "submission_id": 122481982, "status": 10, "contest_id": 59, "data_region": "US", "fail_count": 0}}, {"693": {"id": 389124, "date": 1507426638, "question_id": 693, "submission_id": 122477693, "status": 10, "contest_id": 59, "data_region": "US", "fail_count": 0}, "694": {"id": 396330, "date": 1507430255, "question_id": 694, "submission_id": 122491907, "status": 10, "contest_id": 59, "data_region": "US", "fail_count": 0}, "695": {"id": 392340, "date": 1507427857, "question_id": 695, "submission_id": 122483215, "status": 10, "contest_id": 59, "data_region": "US", "fail_count": 0}}, {"693": {"id": 391506, "date": 1507427499, "question_id": 693, "submission_id": 122481673, "status": 10, "contest_id": 59, "data_region": "US", "fail_count": 1}, "694": {"id": 395890, "date": 1507429962, "question_id": 694, "submission_id": 122490841, "status": 10, "contest_id": 59, "data_region": "US", "fail_count": 0}, "695": {"id": 390245, "date": 1507427015, "question_id": 695, "submission_id": 122479479, "status": 10, "contest_id": 59, "data_region": "US", "fail_count": 0}}, {"693": {"id": 388611, "date": 1507426462, "question_id": 693, "submission_id": 122476851, "status": 10, "contest_id": 59, "data_region": "US", "fail_count": 0}, "694": {"id": 396353, "date": 1507430267, "question_id": 694, "submission_id": 122491959, "status": 10, "contest_id": 59, "data_region": "US", "fail_count": 0}, "695": {"id": 390695, "date": 1507427182, "question_id": 695, "submission_id": 122480224, "status": 10, "contest_id": 59, "data_region": "US", "fail_count": 0}}, {"693": {"id": 389255, "date": 1507426683, "question_id": 693, "submission_id": 122477902, "status": 10, "contest_id": 59, "data_region": "US", "fail_count": 0}, "694": {"id": 395924, "date": 1507429980, "question_id": 694, "submission_id": 122490914, "status": 10, "contest_id": 59, "data_region": "US", "fail_count": 0}, "695": {"id": 392688, "date": 1507428024, "question_id": 695, "submission_id": 122483844, "status": 10, "contest_id": 59, "data_region": "US", "fail_count": 1}}, {"693": {"id": 390092, "date": 1507426962, "question_id": 693, "submission_id": 122479225, "status": 10, "contest_id": 59, "data_region": "US", "fail_count": 0}, "694": {"id": 395042, "date": 1507429394, "question_id": 694, "submission_id": 122488833, "status": 10, "contest_id": 59, "data_region": "US", "fail_count": 3}, "695": {"id": 393112, "date": 1507428243, "question_id": 695, "submission_id": 122484700, "status": 10, "contest_id": 59, "data_region": "US", "fail_count": 0}}, {"693": {"id": 390662, "date": 1507427167, "question_id": 693, "submission_id": 122480155, "status": 10, "contest_id": 59, "data_region": "US", "fail_count": 0}, "694": {"id": 396392, "date": 1507430294, "question_id": 694, "submission_id": 122492070, "status": 10, "contest_id": 59, "data_region": "US", "fail_count": 0}, "695": {"id": 395064, "date": 1507429408, "question_id": 695, "submission_id": 122488877, "status": 10, "contest_id": 59, "data_region": "US", "fail_count": 0}}, {"693": {"id": 390326, "date": 1507427046, "question_id": 693, "submission_id": 122479616, "status": 10, "contest_id": 59, "data_region": "US", "fail_count": 2}, "694": {"id": 394571, "date": 1507429095, "question_id": 694, "submission_id": 122487805, "status": 10, "contest_id": 59, "data_region": "US", "fail_count": 2}, "695": {"id": 392230, "date": 1507427811, "question_id": 695, "submission_id": 122483028, "status": 10, "contest_id": 59, "data_region": "US", "fail_count": 0}}, {"693": {"id": 390885, "date": 1507427249, "question_id": 693, "submission_id": 122480555, "status": 10, "contest_id": 59, "data_region": "US", "fail_count": 1}, "694": {"id": 394577, "date": 1507429097, "question_id": 694, "submission_id": 122487813, "status": 10, "contest_id": 59, "data_region": "US", "fail_count": 1}, "695": {"id": 393064, "date": 1507428219, "question_id": 695, "submission_id": 122484604, "status": 10, "contest_id": 59, "data_region": "US", "fail_count": 2}}, {"693": {"id": 388508, "date": 1507426419, "question_id": 693, "submission_id": 122476665, "status": 10, "contest_id": 59, "data_region": "US", "fail_count": 0}, "694": {"id": 394105, "date": 1507428798, "question_id": 694, "submission_id": 122486767, "status": 10, "contest_id": 59, "data_region": "US", "fail_count": 4}, "695": {"id": 390478, "date": 1507427102, "question_id": 695, "submission_id": 122479875, "status": 10, "contest_id": 59, "data_region": "US", "fail_count": 1}}, {"693": {"id": 388424, "date": 1507426371, "question_id": 693, "submission_id": 122476469, "status": 10, "contest_id": 59, "data_region": "US", "fail_count": 0}, "694": {"id": 395054, "date": 1507429399, "question_id": 694, "submission_id": 122488856, "status": 10, "contest_id": 59, "data_region": "US", "fail_count": 1}, "695": {"id": 392441, "date": 1507427904, "question_id": 695, "submission_id": 122483393, "status": 10, "contest_id": 59, "data_region": "US", "fail_count": 2}}, {"693": {"id": 394048, "date": 1507428764, "question_id": 693, "submission_id": 122486661, "status": 10, "contest_id": 59, "data_region": "US", "fail_count": 0}, "694": {"id": 396400, "date": 1507430300, "question_id": 694, "submission_id": 122492092, "status": 10, "contest_id": 59, "data_region": "US", "fail_count": 0}, "695": {"id": 394983, "date": 1507429360, "question_id": 695, "submission_id": 122488710, "status": 10, "contest_id": 59, "data_region": "US", "fail_count": 0}}, {"693": {"id": 390855, "date": 1507427238, "question_id": 693, "submission_id": 122480499, "status": 10, "contest_id": 59, "data_region": "US", "fail_count": 2}, "694": {"id": 395061, "date": 1507429406, "question_id": 694, "submission_id": 122488869, "status": 10, "contest_id": 59, "data_region": "US", "fail_count": 1}, "695": {"id": 391854, "date": 1507427638, "question_id": 695, "submission_id": 122482291, "status": 10, "contest_id": 59, "data_region": "US", "fail_count": 0}}, {"693": {"id": 388873, "date": 1507426553, "question_id": 693, "submission_id": 122477282, "status": 10, "contest_id": 59, "data_region": "US", "fail_count": 0}, "694": {"id": 396426, "date": 1507430319, "question_id": 694, "submission_id": 122492160, "status": 10, "contest_id": 59, "data_region": "US", "fail_count": 0}, "695": {"id": 390522, "date": 1507427116, "question_id": 695, "submission_id": 122479941, "status": 10, "contest_id": 59, "data_region": "US", "fail_count": 0}}, {"693": {"id": 389916, "date": 1507426902, "question_id": 693, "submission_id": 122478940, "status": 10, "contest_id": 59, "data_region": "US", "fail_count": 0}, "694": {"id": 395538, "date": 1507429725, "question_id": 694, "submission_id": 122489985, "status": 10, "contest_id": 59, "data_region": "US", "fail_count": 2}, "695": {"id": 392065, "date": 1507427734, "question_id": 695, "submission_id": 122482696, "status": 10, "contest_id": 59, "data_region": "US", "fail_count": 0}}, {"693": {"id": 388457, "date": 1507426394, "question_id": 693, "submission_id": 122476564, "status": 10, "contest_id": 59, "data_region": "US", "fail_count": 0}, "694": {"id": 395545, "date": 1507429734, "question_id": 694, "submission_id": 122490008, "status": 10, "contest_id": 59, "data_region": "US", "fail_count": 2}, "695": {"id": 390906, "date": 1507427256, "question_id": 695, "submission_id": 122480590, "status": 10, "contest_id": 59, "data_region": "US", "fail_count": 0}}, {"693": {"id": 389278, "date": 1507426692, "question_id": 693, "submission_id": 122477948, "status": 10, "contest_id": 59, "data_region": "US", "fail_count": 0}, "694": {"id": 395996, "date": 1507430036, "question_id": 694, "submission_id": 122491126, "status": 10, "contest_id": 59, "data_region": "US", "fail_count": 1}, "695": {"id": 391955, "date": 1507427682, "question_id": 695, "submission_id": 122482489, "status": 10, "contest_id": 59, "data_region": "US", "fail_count": 0}}, {"693": {"id": 391160, "date": 1507427371, "question_id": 693, "submission_id": 122481082, "status": 10, "contest_id": 59, "data_region": "US", "fail_count": 0}, "694": {"id": 396013, "date": 1507430044, "question_id": 694, "submission_id": 122491159, "status": 10, "contest_id": 59, "data_region": "US", "fail_count": 1}, "695": {"id": 392282, "date": 1507427833, "question_id": 695, "submission_id": 122483125, "status": 10, "contest_id": 59, "data_region": "US", "fail_count": 0}}], "questions": [{"id": 228, "question_id": 693, "credit": 3, "title": "Binary Number with Alternating Bits", "title_slug": "binary-number-with-alternating-bits"}, {"id": 229, "question_id": 695, "credit": 5, "title": "Max Area of Island", "title_slug": "max-area-of-island"}, {"id": 230, "question_id": 694, "credit": 7, "title": "Number of Distinct Islands", "title_slug": "number-of-distinct-islands"}, {"id": 231, "question_id": 691, "credit": 9, "title": "Stickers to Spell Word", "title_slug": "stickers-to-spell-word"}], "total_rank": [{"contest_id": 59, "username": "hsah", "user_slug": "hsah", "country_code": "US", "country_name": "United States", "rank": 451, "score": 15, "finish_time": 1507430218, "global_ranking": 0, "data_region": "US"}, {"contest_id": 59, "username": "luwanjiu", "user_slug": "luwanjiu", "country_code": "US", "country_name": "United States", "rank": 452, "score": 15, "finish_time": 1507430219, "global_ranking": 0, "data_region": "US"}, {"contest_id": 59, "username": "Bingran_Li", "user_slug": "bingran_li", "country_code": "US", "country_name": "United States", "rank": 453, "score": 15, "finish_time": 1507430230, "global_ranking": 0, "data_region": "US"}, {"contest_id": 59, "username": "lilidavid", "user_slug": "lilidavid", "country_code": "US", "country_name": "United States", "rank": 454, "score": 15, "finish_time": 1507430231, "global_ranking": 0, "data_region": "US"}, {"contest_id": 59, "username": "kaijieqin", "user_slug": "kaijieqin", "country_code": "AS", "country_name": "American Samoa", "rank": 455, "score": 15, "finish_time": 1507430234, "global_ranking": 0, "data_region": "US"}, {"contest_id": 59, "username": "wangjundi2010", "user_slug": "wangjundi2010", "country_code": "US", "country_name": "United States", "rank": 456, "score": 15, "finish_time": 1507430244, "global_ranking": 0, "data_region": "US"}, {"contest_id": 59, "username": "payall4u", "user_slug": "payall4u", "country_code": "CN", "country_name": "China", "rank": 457, "score": 15, "finish_time": 1507430250, "global_ranking": 0, "data_region": "US"}, {"contest_id": 59, "username": "YupengGu", "user_slug": "yupenggu", "country_code": "US", "country_name": "United States", "rank": 458, "score": 15, "finish_time": 1507430255, "global_ranking": 0, "data_region": "US"}, {"contest_id": 59, "username": "sajad", "user_slug": "sajad", "country_code": "US", "country_name": "United States", "rank": 459, "score": 15, "finish_time": 1507430255, "global_ranking": 0, "data_region": "US"}, {"contest_id": 59, "username": "leslie3377", "user_slug": "leslie3377", "country_code": "CN", "country_name": "China", "rank": 460, "score": 15, "finish_time": 1507430262, "global_ranking": 0, "data_region": "US"}, {"contest_id": 59, "username": "zhanglu1990", "user_slug": "zhanglu1990", "country_code": "CN", "country_name": "China", "rank": 461, "score": 15, "finish_time": 1507430267, "global_ranking": 0, "data_region": "US"}, {"contest_id": 59, "username": "hczhong", "user_slug": "hczhong", "country_code": "CN", "country_name": "China", "rank": 462, "score": 15, "finish_time": 1507430280, "global_ranking": 0, "data_region": "US"}, {"contest_id": 59, "username": "yzeng61987", "user_slug": "yzeng61987", "country_code": "US", "country_name": "United States", "rank": 463, "score": 15, "finish_time": 1507430294, "global_ranking": 0, "data_region": "US"}, {"contest_id": 59, "username": "Gengjie", "user_slug": "gengjie", "country_code": "HK", "country_name": "Hong Kong", "rank": 464, "score": 15, "finish_time": 1507430294, "global_ranking": 0, "data_region": "US"}, {"contest_id": 59, "username": "305326653", "user_slug": "305326653", "country_code": "CN", "country_name": "China", "rank": 465, "score": 15, "finish_time": 1507430295, "global_ranking": 0, "data_region": "US"}, {"contest_id": 59, "username": "eggar", "user_slug": "eggar", "country_code": "US", "country_name": "United States", "rank": 466, "score": 15, "finish_time": 1507430297, "global_ranking": 0, "data_region": "US"}, {"contest_id": 59, "username": "perry304", "user_slug": "perry304", "country_code": "US", "country_name": "United States", "rank": 467, "score": 15, "finish_time": 1507430298, "global_ranking": 0, "data_region": "US"}, {"contest_id": 59, "username": "zhun", "user_slug": "zhun", "country_code": "US", "country_name": "United States", "rank": 468, "score": 15, "finish_time": 1507430299, "global_ranking": 0, "data_region": "US"}, {"contest_id": 59, "username": "krpopo", "user_slug": "krpopo", "country_code": "US", "country_name": "United States", "rank": 469, "score": 15, "finish_time": 1507430300, "global_ranking": 0, "data_region": "US"}, {"contest_id": 59, "username": "abdullahamcs", "user_slug": "abdullahamcs", "country_code": "US", "country_name": "United States", "rank": 470, "score": 15, "finish_time": 1507430306, "global_ranking": 0, "data_region": "US"}, {"contest_id": 59, "username": "wenzezhong", "user_slug": "wenzezhong", "country_code": "US", "country_name": "United States", "rank": 471, "score": 15, "finish_time": 1507430319, "global_ranking": 0, "data_region": "US"}, {"contest_id": 59, "username": "talkscheap", "user_slug": "talkscheap", "country_code": "US", "country_name": "United States", "rank": 472, "score": 15, "finish_time": 1507430325, "global_ranking": 0, "data_region": "US"}, {"contest_id": 59, "username": "mze5111", "user_slug": "mze5111", "country_code": "US", "country_name": "United States", "rank": 473, "score": 15, "finish_time": 1507430334, "global_ranking": 0, "data_region": "US"}, {"contest_id": 59, "username": "mbinary", "user_slug": "mbinary", "country_code": "CN", "country_name": "China", "rank": 474, "score": 15, "finish_time": 1507430336, "global_ranking": 0, "data_region": "US"}, {"contest_id": 59, "username": "rahulgutal4", "user_slug": "rahulgutal4", "country_code": "US", "country_name": "United States", "rank": 475, "score": 15, "finish_time": 1507430344, "global_ranking": 0, "data_region": "US"}], "user_num": 2934}