{"time": 1589015420.2427068, "is_past": true, "submissions": [{"1476": {"id": 307105, "date": 1581820787, "question_id": 1476, "submission_id": 47532563, "status": 10, "contest_id": 147, "data_region": "CN", "fail_count": 0}, "1477": {"id": 312299, "date": 1581823601, "question_id": 1477, "submission_id": 47545229, "status": 10, "contest_id": 147, "data_region": "CN", "fail_count": 3}}, {"1476": {"id": 1946716, "date": 1581820304, "question_id": 1476, "submission_id": 303649544, "status": 10, "contest_id": 310, "data_region": "US", "fail_count": 0}, "1477": {"id": 1966310, "date": 1581824203, "question_id": 1477, "submission_id": 303685908, "status": 10, "contest_id": 310, "data_region": "US", "fail_count": 1}}, {"1476": {"id": 1946499, "date": 1581820284, "question_id": 1476, "submission_id": 303649251, "status": 10, "contest_id": 310, "data_region": "US", "fail_count": 0}, "1477": {"id": 1967670, "date": 1581824508, "question_id": 1477, "submission_id": 303688629, "status": 10, "contest_id": 310, "data_region": "US", "fail_count": 0}}, {"1476": {"id": 306287, "date": 1581820422, "question_id": 1476, "submission_id": 47531088, "status": 10, "contest_id": 147, "data_region": "CN", "fail_count": 0}, "1477": {"id": 311399, "date": 1581823010, "question_id": 1477, "submission_id": 47542639, "status": 10, "contest_id": 147, "data_region": "CN", "fail_count": 5}}, {"1476": {"id": 1947420, "date": 1581820383, "question_id": 1476, "submission_id": 303650590, "status": 10, "contest_id": 310, "data_region": "US", "fail_count": 0}, "1477": {"id": 1963520, "date": 1581823613, "question_id": 1477, "submission_id": 303680311, "status": 10, "contest_id": 310, "data_region": "US", "fail_count": 3}}, {"1476": {"id": 1956738, "date": 1581822128, "question_id": 1476, "submission_id": 303667094, "status": 10, "contest_id": 310, "data_region": "US", "fail_count": 0}, "1477": {"id": 1966377, "date": 1581824220, "question_id": 1477, "submission_id": 303686067, "status": 10, "contest_id": 310, "data_region": "US", "fail_count": 1}}, {"1476": {"id": 1955480, "date": 1581821846, "question_id": 1476, "submission_id": 303664714, "status": 10, "contest_id": 310, "data_region": "US", "fail_count": 0}, "1477": {"id": 1965012, "date": 1581823921, "question_id": 1477, "submission_id": 303683249, "status": 10, "contest_id": 310, "data_region": "US", "fail_count": 2}}, {"1476": {"id": 306974, "date": 1581820725, "question_id": 1476, "submission_id": 47532299, "status": 10, "contest_id": 147, "data_region": "CN", "fail_count": 0}, "1478": {"id": 312768, "date": 1581823923, "question_id": 1478, "submission_id": 47546599, "status": 10, "contest_id": 147, "data_region": "CN", "fail_count": 2}}, {"1476": {"id": 306001, "date": 1581820327, "question_id": 1476, "submission_id": 47530607, "status": 10, "contest_id": 147, "data_region": "CN", "fail_count": 0}, "1477": {"id": 311418, "date": 1581823024, "question_id": 1477, "submission_id": 47542703, "status": 10, "contest_id": 147, "data_region": "CN", "fail_count": 5}}, {"1476": {"id": 1954984, "date": 1581821744, "question_id": 1476, "submission_id": 303663798, "status": 10, "contest_id": 310, "data_region": "US", "fail_count": 0}, "1477": {"id": 1966433, "date": 1581824232, "question_id": 1477, "submission_id": 303686178, "status": 10, "contest_id": 310, "data_region": "US", "fail_count": 1}}, {"1476": {"id": 1946828, "date": 1581820314, "question_id": 1476, "submission_id": 303649702, "status": 10, "contest_id": 310, "data_region": "US", "fail_count": 0}, "1477": {"id": 1959509, "date": 1581822732, "question_id": 1477, "submission_id": 303672346, "status": 10, "contest_id": 310, "data_region": "US", "fail_count": 6}}, {"1476": {"id": 309171, "date": 1581821718, "question_id": 1476, "submission_id": 47536869, "status": 10, "contest_id": 147, "data_region": "CN", "fail_count": 2}, "1477": {"id": 311888, "date": 1581823334, "question_id": 1477, "submission_id": 47544028, "status": 10, "contest_id": 147, "data_region": "CN", "fail_count": 2}}, {"1476": {"id": 306286, "date": 1581820422, "question_id": 1476, "submission_id": 47531087, "status": 10, "contest_id": 147, "data_region": "CN", "fail_count": 0}, "1477": {"id": 313194, "date": 1581824236, "question_id": 1477, "submission_id": 47547947, "status": 10, "contest_id": 147, "data_region": "CN", "fail_count": 1}}, {"1476": {"id": 1951486, "date": 1581821046, "question_id": 1476, "submission_id": 303657373, "status": 10, "contest_id": 310, "data_region": "US", "fail_count": 0}, "1477": {"id": 1963632, "date": 1581823638, "question_id": 1477, "submission_id": 303680535, "status": 10, "contest_id": 310, "data_region": "US", "fail_count": 3}}, {"1476": {"id": 309060, "date": 1581821658, "question_id": 1476, "submission_id": 47536607, "status": 10, "contest_id": 147, "data_region": "CN", "fail_count": 1}, "1477": {"id": 312353, "date": 1581823640, "question_id": 1477, "submission_id": 47545375, "status": 10, "contest_id": 147, "data_region": "CN", "fail_count": 2}}, {"1476": {"id": 1946733, "date": 1581820305, "question_id": 1476, "submission_id": 303649570, "status": 10, "contest_id": 310, "data_region": "US", "fail_count": 0}, "1477": {"id": 1966483, "date": 1581824243, "question_id": 1477, "submission_id": 303686285, "status": 10, "contest_id": 310, "data_region": "US", "fail_count": 1}}, {"1476": {"id": 1947499, "date": 1581820394, "question_id": 1476, "submission_id": 303650709, "status": 10, "contest_id": 310, "data_region": "US", "fail_count": 0}, "1477": {"id": 1967817, "date": 1581824544, "question_id": 1477, "submission_id": 303688945, "status": 10, "contest_id": 310, "data_region": "US", "fail_count": 0}}, {"1476": {"id": 1947098, "date": 1581820342, "question_id": 1476, "submission_id": 303650080, "status": 10, "contest_id": 310, "data_region": "US", "fail_count": 0}, "1477": {"id": 1962311, "date": 1581823345, "question_id": 1477, "submission_id": 303677777, "status": 10, "contest_id": 310, "data_region": "US", "fail_count": 4}}, {"1476": {"id": 1946999, "date": 1581820330, "question_id": 1476, "submission_id": 303649938, "status": 10, "contest_id": 310, "data_region": "US", "fail_count": 0}, "1477": {"id": 1966493, "date": 1581824245, "question_id": 1477, "submission_id": 303686302, "status": 10, "contest_id": 310, "data_region": "US", "fail_count": 1}}, {"1476": {"id": 1946884, "date": 1581820319, "question_id": 1476, "submission_id": 303649779, "status": 10, "contest_id": 310, "data_region": "US", "fail_count": 0}, "1477": {"id": 1958197, "date": 1581822446, "question_id": 1477, "submission_id": 303669901, "status": 10, "contest_id": 310, "data_region": "US", "fail_count": 7}}, {"1476": {"id": 1949831, "date": 1581820757, "question_id": 1476, "submission_id": 303654406, "status": 10, "contest_id": 310, "data_region": "US", "fail_count": 1}, "1477": {"id": 1963667, "date": 1581823646, "question_id": 1477, "submission_id": 303680604, "status": 10, "contest_id": 310, "data_region": "US", "fail_count": 2}}, {"1476": {"id": 1949070, "date": 1581820632, "question_id": 1476, "submission_id": 303653157, "status": 10, "contest_id": 310, "data_region": "US", "fail_count": 0}, "1477": {"id": 1965155, "date": 1581823951, "question_id": 1477, "submission_id": 303683542, "status": 10, "contest_id": 310, "data_region": "US", "fail_count": 2}}, {"1476": {"id": 1946987, "date": 1581820329, "question_id": 1476, "submission_id": 303649924, "status": 10, "contest_id": 310, "data_region": "US", "fail_count": 0}, "1477": {"id": 1966522, "date": 1581824252, "question_id": 1477, "submission_id": 303686356, "status": 10, "contest_id": 310, "data_region": "US", "fail_count": 1}}, {"1476": {"id": 1950151, "date": 1581820808, "question_id": 1476, "submission_id": 303654953, "status": 10, "contest_id": 310, "data_region": "US", "fail_count": 0}, "1477": {"id": 1965170, "date": 1581823953, "question_id": 1477, "submission_id": 303683569, "status": 10, "contest_id": 310, "data_region": "US", "fail_count": 2}}, {"1476": {"id": 1948018, "date": 1581820468, "question_id": 1476, "submission_id": 303651496, "status": 10, "contest_id": 310, "data_region": "US", "fail_count": 0}, "1478": {"id": 1967886, "date": 1581824563, "question_id": 1478, "submission_id": 303689089, "status": 10, "contest_id": 310, "data_region": "US", "fail_count": 0}}], "questions": [{"id": 1238, "question_id": 1476, "credit": 3, "title": "Count Negative Numbers in a Sorted Matrix", "title_slug": "count-negative-numbers-in-a-sorted-matrix"}, {"id": 1239, "question_id": 1477, "credit": 5, "title": "Product of the Last K Numbers", "title_slug": "product-of-the-last-k-numbers"}, {"id": 1240, "question_id": 1478, "credit": 5, "title": "Maximum Number of Events That Can Be Attended", "title_slug": "maximum-number-of-events-that-can-be-attended"}, {"id": 1241, "question_id": 1479, "credit": 6, "title": "Construct Target Array With Multiple Sums", "title_slug": "construct-target-array-with-multiple-sums"}], "total_rank": [{"contest_id": 147, "username": "cnkoala", "user_slug": "cnkoala", "country_code": "", "country_name": null, "rank": 3351, "score": 8, "finish_time": 1581824501, "global_ranking": 0, "data_region": "CN"}, {"contest_id": 310, "username": "elleryqueenhomels", "user_slug": "elleryqueenhomels", "country_code": "", "country_name": null, "rank": 3352, "score": 8, "finish_time": 1581824503, "global_ranking": 0, "data_region": "US"}, {"contest_id": 310, "username": "lemiao", "user_slug": "lemiao", "country_code": "", "country_name": null, "rank": 3353, "score": 8, "finish_time": 1581824508, "global_ranking": 0, "data_region": "US"}, {"contest_id": 147, "username": "li-kou-xie-fei-ji", "user_slug": "li-kou-xie-fei-ji", "country_code": "", "country_name": null, "rank": 3354, "score": 8, "finish_time": 1581824510, "global_ranking": 0, "data_region": "CN"}, {"contest_id": 310, "username": "polavishnu", "user_slug": "polavishnu", "country_code": "IN", "country_name": "India", "rank": 3355, "score": 8, "finish_time": 1581824513, "global_ranking": 0, "data_region": "US"}, {"contest_id": 310, "username": "mussumd11", "user_slug": "mussumd11", "country_code": "", "country_name": null, "rank": 3356, "score": 8, "finish_time": 1581824520, "global_ranking": 0, "data_region": "US"}, {"contest_id": 310, "username": "utsav0202", "user_slug": "utsav0202", "country_code": "", "country_name": null, "rank": 3357, "score": 8, "finish_time": 1581824521, "global_ranking": 0, "data_region": "US"}, {"contest_id": 147, "username": "movetobe", "user_slug": "movetobe", "country_code": "", "country_name": null, "rank": 3358, "score": 8, "finish_time": 1581824523, "global_ranking": 0, "data_region": "CN"}, {"contest_id": 147, "username": "wu-wu-lu-lu", "user_slug": "wu-wu-lu-lu", "country_code": "", "country_name": null, "rank": 3359, "score": 8, "finish_time": 1581824524, "global_ranking": 0, "data_region": "CN"}, {"contest_id": 310, "username": "statics86", "user_slug": "statics86", "country_code": "", "country_name": null, "rank": 3360, "score": 8, "finish_time": 1581824532, "global_ranking": 0, "data_region": "US"}, {"contest_id": 310, "username": "yama1223xxx", "user_slug": "yama1223xxx", "country_code": "JP", "country_name": "Japan", "rank": 3361, "score": 8, "finish_time": 1581824532, "global_ranking": 0, "data_region": "US"}, {"contest_id": 147, "username": "xiaoqixian", "user_slug": "xiaoqixian", "country_code": "", "country_name": null, "rank": 3362, "score": 8, "finish_time": 1581824534, "global_ranking": 0, "data_region": "CN"}, {"contest_id": 147, "username": "zdxiq125", "user_slug": "zdxiq125", "country_code": "", "country_name": null, "rank": 3363, "score": 8, "finish_time": 1581824536, "global_ranking": 0, "data_region": "CN"}, {"contest_id": 310, "username": "MccreeFei", "user_slug": "mccreefei", "country_code": "", "country_name": null, "rank": 3364, "score": 8, "finish_time": 1581824538, "global_ranking": 0, "data_region": "US"}, {"contest_id": 147, "username": "hwlei", "user_slug": "hwlei", "country_code": "", "country_name": null, "rank": 3365, "score": 8, "finish_time": 1581824540, "global_ranking": 0, "data_region": "CN"}, {"contest_id": 310, "username": "wanghezhi", "user_slug": "wanghezhi", "country_code": "", "country_name": "", "rank": 3366, "score": 8, "finish_time": 1581824543, "global_ranking": 0, "data_region": "US"}, {"contest_id": 310, "username": "studentforlife", "user_slug": "studentforlife", "country_code": "US", "country_name": "United States", "rank": 3367, "score": 8, "finish_time": 1581824544, "global_ranking": 0, "data_region": "US"}, {"contest_id": 310, "username": "xuzheng1994620", "user_slug": "xuzheng1994620", "country_code": "", "country_name": null, "rank": 3368, "score": 8, "finish_time": 1581824545, "global_ranking": 0, "data_region": "US"}, {"contest_id": 310, "username": "laurence-ling", "user_slug": "laurence-ling", "country_code": "", "country_name": null, "rank": 3369, "score": 8, "finish_time": 1581824545, "global_ranking": 0, "data_region": "US"}, {"contest_id": 310, "username": "KovuriVinay", "user_slug": "kovurivinay", "country_code": "", "country_name": null, "rank": 3370, "score": 8, "finish_time": 1581824546, "global_ranking": 0, "data_region": "US"}, {"contest_id": 310, "username": "xucode", "user_slug": "xucode", "country_code": "US", "country_name": "United States", "rank": 3371, "score": 8, "finish_time": 1581824546, "global_ranking": 0, "data_region": "US"}, {"contest_id": 310, "username": "sumi_9648", "user_slug": "sumi_9648", "country_code": "JP", "country_name": "Japan", "rank": 3372, "score": 8, "finish_time": 1581824551, "global_ranking": 0, "data_region": "US"}, {"contest_id": 310, "username": "GongYoo", "user_slug": "gongyoo", "country_code": "", "country_name": null, "rank": 3373, "score": 8, "finish_time": 1581824552, "global_ranking": 0, "data_region": "US"}, {"contest_id": 310, "username": "mukundv18", "user_slug": "mukundv18", "country_code": "", "country_name": null, "rank": 3374, "score": 8, "finish_time": 1581824553, "global_ranking": 0, "data_region": "US"}, {"contest_id": 310, "username": "paranan", "user_slug": "paranan", "country_code": "IN", "country_name": "India", "rank": 3375, "score": 8, "finish_time": 1581824563, "global_ranking": 0, "data_region": "US"}], "user_num": 8106}