{"time": 1600278048.8422854, "is_past": true, "submissions": [{"696": {"id": 401173, "date": 1508032720, "question_id": 696, "submission_id": 123600959, "status": 10, "contest_id": 60, "data_region": "US", "fail_count": 0}, "697": {"id": 399760, "date": 1508032086, "question_id": 697, "submission_id": 123598386, "status": 10, "contest_id": 60, "data_region": "US", "fail_count": 1}, "698": {"id": 406446, "date": 1508035616, "question_id": 698, "submission_id": 123612179, "status": 10, "contest_id": 60, "data_region": "US", "fail_count": 2}}, {"696": {"id": 402401, "date": 1508033320, "question_id": 696, "submission_id": 123603268, "status": 10, "contest_id": 60, "data_region": "US", "fail_count": 0}, "697": {"id": 400856, "date": 1508032575, "question_id": 697, "submission_id": 123600361, "status": 10, "contest_id": 60, "data_region": "US", "fail_count": 0}, "698": {"id": 407001, "date": 1508035917, "question_id": 698, "submission_id": 123613373, "status": 10, "contest_id": 60, "data_region": "US", "fail_count": 2}}, {"696": {"id": 401426, "date": 1508032831, "question_id": 696, "submission_id": 123601401, "status": 10, "contest_id": 60, "data_region": "US", "fail_count": 1}, "697": {"id": 398754, "date": 1508031586, "question_id": 697, "submission_id": 123596364, "status": 10, "contest_id": 60, "data_region": "US", "fail_count": 0}, "698": {"id": 407019, "date": 1508035928, "question_id": 698, "submission_id": 123613422, "status": 10, "contest_id": 60, "data_region": "US", "fail_count": 1}}, {"696": {"id": 401609, "date": 1508032921, "question_id": 696, "submission_id": 123601742, "status": 10, "contest_id": 60, "data_region": "US", "fail_count": 0}, "697": {"id": 399119, "date": 1508031788, "question_id": 697, "submission_id": 123597142, "status": 10, "contest_id": 60, "data_region": "US", "fail_count": 0}, "698": {"id": 404993, "date": 1508034757, "question_id": 698, "submission_id": 123608831, "status": 10, "contest_id": 60, "data_region": "US", "fail_count": 6}}, {"696": {"id": 403711, "date": 1508033999, "question_id": 696, "submission_id": 123605958, "status": 10, "contest_id": 60, "data_region": "US", "fail_count": 0}, "697": {"id": 406538, "date": 1508035671, "question_id": 697, "submission_id": 123612383, "status": 10, "contest_id": 60, "data_region": "US", "fail_count": 2}, "698": {"id": 402022, "date": 1508033122, "question_id": 698, "submission_id": 123602484, "status": 10, "contest_id": 60, "data_region": "US", "fail_count": 1}}, {"696": {"id": 405680, "date": 1508035163, "question_id": 696, "submission_id": 123610428, "status": 10, "contest_id": 60, "data_region": "US", "fail_count": 1}, "697": {"id": 402159, "date": 1508033197, "question_id": 697, "submission_id": 123602775, "status": 10, "contest_id": 60, "data_region": "US", "fail_count": 0}, "698": {"id": 407687, "date": 1508036283, "question_id": 698, "submission_id": 123614887, "status": 10, "contest_id": 60, "data_region": "US", "fail_count": 0}}, {"696": {"id": 403155, "date": 1508033709, "question_id": 696, "submission_id": 123604778, "status": 10, "contest_id": 60, "data_region": "US", "fail_count": 6}, "697": {"id": 404454, "date": 1508034440, "question_id": 697, "submission_id": 123607685, "status": 10, "contest_id": 60, "data_region": "US", "fail_count": 0}, "698": {"id": 405084, "date": 1508034806, "question_id": 698, "submission_id": 123609020, "status": 10, "contest_id": 60, "data_region": "US", "fail_count": 0}}, {"696": {"id": 402059, "date": 1508033145, "question_id": 696, "submission_id": 123602570, "status": 10, "contest_id": 60, "data_region": "US", "fail_count": 0}, "697": {"id": 398888, "date": 1508031669, "question_id": 697, "submission_id": 123596658, "status": 10, "contest_id": 60, "data_region": "US", "fail_count": 0}, "698": {"id": 407772, "date": 1508036316, "question_id": 698, "submission_id": 123615048, "status": 10, "contest_id": 60, "data_region": "US", "fail_count": 1}}, {"696": {"id": 399755, "date": 1508032083, "question_id": 696, "submission_id": 123598375, "status": 10, "contest_id": 60, "data_region": "US", "fail_count": 0}, "697": {"id": 398691, "date": 1508031529, "question_id": 697, "submission_id": 123596178, "status": 10, "contest_id": 60, "data_region": "US", "fail_count": 0}, "698": {"id": 407783, "date": 1508036319, "question_id": 698, "submission_id": 123615062, "status": 10, "contest_id": 60, "data_region": "US", "fail_count": 1}}, {"696": {"id": 403553, "date": 1508033919, "question_id": 696, "submission_id": 123605631, "status": 10, "contest_id": 60, "data_region": "US", "fail_count": 0}, "697": {"id": 398860, "date": 1508031652, "question_id": 697, "submission_id": 123596598, "status": 10, "contest_id": 60, "data_region": "US", "fail_count": 0}, "698": {"id": 407194, "date": 1508036027, "question_id": 698, "submission_id": 123613836, "status": 10, "contest_id": 60, "data_region": "US", "fail_count": 2}}, {"696": {"id": 399506, "date": 1508031972, "question_id": 696, "submission_id": 123597886, "status": 10, "contest_id": 60, "data_region": "US", "fail_count": 0}, "697": {"id": 398723, "date": 1508031564, "question_id": 697, "submission_id": 123596285, "status": 10, "contest_id": 60, "data_region": "US", "fail_count": 0}, "698": {"id": 407195, "date": 1508036029, "question_id": 698, "submission_id": 123613839, "status": 10, "contest_id": 60, "data_region": "US", "fail_count": 2}}, {"696": {"id": 406654, "date": 1508035727, "question_id": 696, "submission_id": 123612624, "status": 10, "contest_id": 60, "data_region": "US", "fail_count": 1}, "697": {"id": 400150, "date": 1508032262, "question_id": 697, "submission_id": 123599095, "status": 10, "contest_id": 60, "data_region": "US", "fail_count": 0}, "698": {"id": 407823, "date": 1508036335, "question_id": 698, "submission_id": 123615126, "status": 10, "contest_id": 60, "data_region": "US", "fail_count": 0}}, {"696": {"id": 402742, "date": 1508033507, "question_id": 696, "submission_id": 123603980, "status": 10, "contest_id": 60, "data_region": "US", "fail_count": 0}, "697": {"id": 400756, "date": 1508032535, "question_id": 697, "submission_id": 123600192, "status": 10, "contest_id": 60, "data_region": "US", "fail_count": 0}, "698": {"id": 407295, "date": 1508036089, "question_id": 698, "submission_id": 123614077, "status": 10, "contest_id": 60, "data_region": "US", "fail_count": 2}}, {"696": {"id": 399495, "date": 1508031969, "question_id": 696, "submission_id": 123597866, "status": 10, "contest_id": 60, "data_region": "US", "fail_count": 0}, "697": {"id": 407303, "date": 1508036091, "question_id": 697, "submission_id": 123614093, "status": 10, "contest_id": 60, "data_region": "US", "fail_count": 1}, "698": {"id": 404110, "date": 1508034255, "question_id": 698, "submission_id": 123606914, "status": 10, "contest_id": 60, "data_region": "US", "fail_count": 1}}, {"696": {"id": 399873, "date": 1508032130, "question_id": 696, "submission_id": 123598584, "status": 10, "contest_id": 60, "data_region": "US", "fail_count": 0}, "697": {"id": 398924, "date": 1508031691, "question_id": 697, "submission_id": 123596747, "status": 10, "contest_id": 60, "data_region": "US", "fail_count": 0}, "698": {"id": 407319, "date": 1508036100, "question_id": 698, "submission_id": 123614124, "status": 10, "contest_id": 60, "data_region": "US", "fail_count": 2}}, {"696": {"id": 401043, "date": 1508032660, "question_id": 696, "submission_id": 123600714, "status": 10, "contest_id": 60, "data_region": "US", "fail_count": 1}, "697": {"id": 398616, "date": 1508031454, "question_id": 697, "submission_id": 123595958, "status": 10, "contest_id": 60, "data_region": "US", "fail_count": 1}, "698": {"id": 405242, "date": 1508034904, "question_id": 698, "submission_id": 123609378, "status": 10, "contest_id": 60, "data_region": "US", "fail_count": 4}}, {"696": {"id": 401475, "date": 1508032855, "question_id": 696, "submission_id": 123601492, "status": 10, "contest_id": 60, "data_region": "US", "fail_count": 0}, "697": {"id": 399772, "date": 1508032091, "question_id": 697, "submission_id": 123598405, "status": 10, "contest_id": 60, "data_region": "US", "fail_count": 0}, "698": {"id": 407353, "date": 1508036115, "question_id": 698, "submission_id": 123614188, "status": 10, "contest_id": 60, "data_region": "US", "fail_count": 2}}, {"696": {"id": 398636, "date": 1508031473, "question_id": 696, "submission_id": 123596011, "status": 10, "contest_id": 60, "data_region": "US", "fail_count": 1}, "697": {"id": 399126, "date": 1508031793, "question_id": 697, "submission_id": 123597155, "status": 10, "contest_id": 60, "data_region": "US", "fail_count": 0}, "698": {"id": 405267, "date": 1508034915, "question_id": 698, "submission_id": 123609429, "status": 10, "contest_id": 60, "data_region": "US", "fail_count": 5}}, {"696": {"id": 403004, "date": 1508033633, "question_id": 696, "submission_id": 123604490, "status": 10, "contest_id": 60, "data_region": "US", "fail_count": 0}, "697": {"id": 400918, "date": 1508032609, "question_id": 697, "submission_id": 123600489, "status": 10, "contest_id": 60, "data_region": "US", "fail_count": 0}, "698": {"id": 407358, "date": 1508036117, "question_id": 698, "submission_id": 123614196, "status": 10, "contest_id": 60, "data_region": "US", "fail_count": 2}}, {"696": {"id": 401288, "date": 1508032766, "question_id": 696, "submission_id": 123601158, "status": 10, "contest_id": 60, "data_region": "US", "fail_count": 0}, "697": {"id": 399323, "date": 1508031891, "question_id": 697, "submission_id": 123597544, "status": 10, "contest_id": 60, "data_region": "US", "fail_count": 0}, "698": {"id": 406284, "date": 1508035528, "question_id": 698, "submission_id": 123611816, "status": 10, "contest_id": 60, "data_region": "US", "fail_count": 4}}, {"696": {"id": 405831, "date": 1508035247, "question_id": 696, "submission_id": 123610745, "status": 10, "contest_id": 60, "data_region": "US", "fail_count": 4}, "697": {"id": 398578, "date": 1508031402, "question_id": 697, "submission_id": 123595802, "status": 10, "contest_id": 60, "data_region": "US", "fail_count": 0}, "698": {"id": 402198, "date": 1508033215, "question_id": 698, "submission_id": 123602848, "status": 10, "contest_id": 60, "data_region": "US", "fail_count": 1}}, {"696": {"id": 405483, "date": 1508035039, "question_id": 696, "submission_id": 123609960, "status": 10, "contest_id": 60, "data_region": "US", "fail_count": 1}, "697": {"id": 400794, "date": 1508032551, "question_id": 697, "submission_id": 123600257, "status": 10, "contest_id": 60, "data_region": "US", "fail_count": 2}, "698": {"id": 406986, "date": 1508035909, "question_id": 698, "submission_id": 123613340, "status": 10, "contest_id": 60, "data_region": "US", "fail_count": 0}}, {"696": {"id": 401397, "date": 1508032818, "question_id": 696, "submission_id": 123601345, "status": 10, "contest_id": 60, "data_region": "US", "fail_count": 0}, "697": {"id": 398876, "date": 1508031661, "question_id": 697, "submission_id": 123596629, "status": 10, "contest_id": 60, "data_region": "US", "fail_count": 0}, "698": {"id": 407002, "date": 1508035918, "question_id": 698, "submission_id": 123613380, "status": 10, "contest_id": 60, "data_region": "US", "fail_count": 3}}, {"696": {"id": 400993, "date": 1508032641, "question_id": 696, "submission_id": 123600627, "status": 10, "contest_id": 60, "data_region": "US", "fail_count": 1}, "697": {"id": 402414, "date": 1508033325, "question_id": 697, "submission_id": 123603293, "status": 10, "contest_id": 60, "data_region": "US", "fail_count": 0}, "698": {"id": 406457, "date": 1508035623, "question_id": 698, "submission_id": 123612203, "status": 10, "contest_id": 60, "data_region": "US", "fail_count": 3}}, {"696": {"id": 403593, "date": 1508033946, "question_id": 696, "submission_id": 123605727, "status": 10, "contest_id": 60, "data_region": "US", "fail_count": 0}, "697": {"id": 402426, "date": 1508033331, "question_id": 697, "submission_id": 123603313, "status": 10, "contest_id": 60, "data_region": "US", "fail_count": 1}, "698": {"id": 407584, "date": 1508036232, "question_id": 698, "submission_id": 123614674, "status": 10, "contest_id": 60, "data_region": "US", "fail_count": 1}}], "questions": [{"id": 232, "question_id": 697, "credit": 3, "title": "Degree of an Array", "title_slug": "degree-of-an-array"}, {"id": 233, "question_id": 696, "credit": 5, "title": "Count Binary Substrings", "title_slug": "count-binary-substrings"}, {"id": 234, "question_id": 698, "credit": 7, "title": "Partition to K Equal Sum Subsets", "title_slug": "partition-to-k-equal-sum-subsets"}, {"id": 235, "question_id": 699, "credit": 10, "title": "Falling Squares", "title_slug": "falling-squares"}], "total_rank": [{"contest_id": 60, "username": "smallman", "user_slug": "smallman", "country_code": "US", "country_name": "United States", "rank": 401, "score": 15, "finish_time": 1508036516, "global_ranking": 0, "data_region": "US"}, {"contest_id": 60, "username": "sunrisef", "user_slug": "sunrisef", "country_code": "US", "country_name": "United States", "rank": 402, "score": 15, "finish_time": 1508036517, "global_ranking": 0, "data_region": "US"}, {"contest_id": 60, "username": "noi10", "user_slug": "noi10", "country_code": "US", "country_name": "United States", "rank": 403, "score": 15, "finish_time": 1508036528, "global_ranking": 0, "data_region": "US"}, {"contest_id": 60, "username": "marco28", "user_slug": "marco28", "country_code": "US", "country_name": "United States", "rank": 404, "score": 15, "finish_time": 1508036557, "global_ranking": 0, "data_region": "US"}, {"contest_id": 60, "username": "yymmyy", "user_slug": "yymmyy", "country_code": "US", "country_name": "United States", "rank": 405, "score": 15, "finish_time": 1508036571, "global_ranking": 0, "data_region": "US"}, {"contest_id": 60, "username": "wty921101", "user_slug": "wty921101", "country_code": "US", "country_name": "United States", "rank": 406, "score": 15, "finish_time": 1508036583, "global_ranking": 0, "data_region": "US"}, {"contest_id": 60, "username": "chunyu3", "user_slug": "chunyu3", "country_code": "", "country_name": null, "rank": 407, "score": 15, "finish_time": 1508036606, "global_ranking": 0, "data_region": "US"}, {"contest_id": 60, "username": "mkuai", "user_slug": "mkuai", "country_code": "US", "country_name": "United States", "rank": 408, "score": 15, "finish_time": 1508036616, "global_ranking": 0, "data_region": "US"}, {"contest_id": 60, "username": "brucezu", "user_slug": "brucezu", "country_code": "US", "country_name": "United States", "rank": 409, "score": 15, "finish_time": 1508036619, "global_ranking": 0, "data_region": "US"}, {"contest_id": 60, "username": "tomerry", "user_slug": "tomerry", "country_code": "CN", "country_name": "China", "rank": 410, "score": 15, "finish_time": 1508036627, "global_ranking": 0, "data_region": "US"}, {"contest_id": 60, "username": "qw123", "user_slug": "qw123", "country_code": "US", "country_name": "United States", "rank": 411, "score": 15, "finish_time": 1508036629, "global_ranking": 0, "data_region": "US"}, {"contest_id": 60, "username": "magicclam", "user_slug": "magicclam", "country_code": "US", "country_name": "United States", "rank": 412, "score": 15, "finish_time": 1508036635, "global_ranking": 0, "data_region": "US"}, {"contest_id": 60, "username": "liweiml", "user_slug": "liweiml", "country_code": "CN", "country_name": "China", "rank": 413, "score": 15, "finish_time": 1508036689, "global_ranking": 0, "data_region": "US"}, {"contest_id": 60, "username": "sudharshan3010", "user_slug": "sudharshan3010", "country_code": "US", "country_name": "United States", "rank": 414, "score": 15, "finish_time": 1508036691, "global_ranking": 0, "data_region": "US"}, {"contest_id": 60, "username": "Chi_Zhang", "user_slug": "chi_zhang", "country_code": "CA", "country_name": "Canada", "rank": 415, "score": 15, "finish_time": 1508036700, "global_ranking": 0, "data_region": "US"}, {"contest_id": 60, "username": "firepaw", "user_slug": "firepaw", "country_code": "CN", "country_name": "China", "rank": 416, "score": 15, "finish_time": 1508036704, "global_ranking": 0, "data_region": "US"}, {"contest_id": 60, "username": "lczazu", "user_slug": "lczazu", "country_code": "CN", "country_name": "China", "rank": 417, "score": 15, "finish_time": 1508036715, "global_ranking": 0, "data_region": "US"}, {"contest_id": 60, "username": "eggeggegg", "user_slug": "eggeggegg", "country_code": "US", "country_name": "United States", "rank": 418, "score": 15, "finish_time": 1508036715, "global_ranking": 0, "data_region": "US"}, {"contest_id": 60, "username": "BrokenDawn", "user_slug": "brokendawn", "country_code": "CN", "country_name": "China", "rank": 419, "score": 15, "finish_time": 1508036717, "global_ranking": 0, "data_region": "US"}, {"contest_id": 60, "username": "1moretry", "user_slug": "1moretry", "country_code": "JP", "country_name": "Japan", "rank": 420, "score": 15, "finish_time": 1508036728, "global_ranking": 0, "data_region": "US"}, {"contest_id": 60, "username": "UnionQ", "user_slug": "unionq", "country_code": "US", "country_name": "United States", "rank": 421, "score": 15, "finish_time": 1508036747, "global_ranking": 0, "data_region": "US"}, {"contest_id": 60, "username": "wendy20501", "user_slug": "wendy20501", "country_code": "US", "country_name": "United States", "rank": 422, "score": 15, "finish_time": 1508036809, "global_ranking": 0, "data_region": "US"}, {"contest_id": 60, "username": "testitest", "user_slug": "testitest", "country_code": "CN", "country_name": "China", "rank": 423, "score": 15, "finish_time": 1508036818, "global_ranking": 0, "data_region": "US"}, {"contest_id": 60, "username": "lovedsp210", "user_slug": "lovedsp210", "country_code": "US", "country_name": "United States", "rank": 424, "score": 15, "finish_time": 1508036823, "global_ranking": 0, "data_region": "US"}, {"contest_id": 60, "username": "luckcul", "user_slug": "luckcul", "country_code": "CN", "country_name": "China", "rank": 425, "score": 15, "finish_time": 1508036832, "global_ranking": 0, "data_region": "US"}], "user_num": 3232}